{
  "concept_a": "biofuel_mandate_credit_rigidity",
  "concept_b": "credit_tightening_commodity_supply_paradox",
  "mechanism": "Legislated biofuel mandates (~40% corn demand, ~35% soybean oil demand) prevent full demand-side adjustment during credit tightening, reinforcing the paradox of credit tightening supporting commodity prices through mandatory demand floors.",
  "direction": "a_causes_b",
  "confidence": 5,
  "regime_dependence": "Active as long as RFS mandates remain. Congress has never reduced ethanol mandates, creating structural demand floor independent of economic cycle.",
  "originating_agents": [
    "commodities_analyst_02"
  ],
  "topic": "credit_cycles",
  "created_at": "2026-03-23T08:42:47Z",
  "last_updated": "2026-03-23T08:42:47Z",
  "originating_iteration": "iter_0028",
  "research_iterations": 1,
  "iteration_history": [
    "iter_0028"
  ]
}
