{
  "concept_a": "fx_adjustment_leads_convergence",
  "concept_b": "boj_normalization_catalyst",
  "mechanism": "FX adjusts faster than central bank committee cycles (structural). BoJ normalization creates rate divergence requiring resolution, and the historical pattern shows FX moves first by 2-6 months before rates converge, implying FX markets will anticipate and front-run BoJ normalization effects.",
  "direction": "correlated",
  "confidence": 7,
  "regime_dependence": "Applies to extreme divergence episodes (>85th percentile rate divergence)",
  "originating_agents": [
    "generalist_02"
  ],
  "topic": "fx_rates_divergence",
  "created_at": "2026-03-22T21:50:58Z",
  "last_updated": "2026-03-22T21:50:58Z",
  "originating_iteration": "iter_0009",
  "research_iterations": 1,
  "iteration_history": [
    "iter_0009"
  ]
}
