{
  "concept_a": "forward_guidance_asymmetric_attenuation",
  "concept_b": "broken_monetary_transmission",
  "mechanism": "Dovish guidance losing ~50% potency under positive correlation while hawkish guidance retains full effect is a specific manifestation of the broader transmission breakdown, creating an asymmetric policy tool less effective when easing is most needed.",
  "direction": "a_causes_b",
  "confidence": 7,
  "regime_dependence": "Only holds under positive or transitional correlation regimes. Under stable negative correlation, dovish guidance should retain full potency as rate cuts signal both lower discount rates and supportive conditions.",
  "originating_agents": [
    "rates_strategist_02"
  ],
  "topic": "rates_equity_correlation",
  "created_at": "2026-03-23T04:13:17Z",
  "last_updated": "2026-03-23T04:13:17Z",
  "originating_iteration": "iter_0020",
  "research_iterations": 1,
  "iteration_history": [
    "iter_0020"
  ]
}
