{
  "concept_a": "usd_self_correcting_reinforcing_loop",
  "concept_b": "central_bank_credibility_anchoring",
  "mechanism": "Fed credibility determines which USD loop operates. When the Fed is perceived as ahead of the curve, the self-correcting loop strengthens the dollar and moderates commodities. When behind the curve, the self-reinforcing loop weakens the dollar and amplifies commodities.",
  "direction": "b_causes_a",
  "confidence": 7,
  "regime_dependence": "The loop identification depends on real-time perception of Fed credibility. Transitions between loops can be abrupt when market consensus shifts (e.g., November 2021 when transitory was abandoned).",
  "originating_agents": [
    "equity_analyst_01"
  ],
  "topic": "commodity_inflation_transmission",
  "created_at": "2026-03-22T19:02:28Z",
  "last_updated": "2026-03-22T19:02:28Z",
  "originating_iteration": "iter_0005",
  "research_iterations": 1,
  "iteration_history": [
    "iter_0005"
  ]
}
