{
  "concept_a": "china_demographic_cliff",
  "concept_b": "simultaneous_global_aging",
  "mechanism": "China's concurrent aging (largest population ever to age) adds ~20% of global GDP to the simultaneously aging bloc, qualitatively changing the nature of global aging from a Japan-specific to a systemic phenomenon",
  "direction": "a_causes_b",
  "confidence": 8,
  "regime_dependence": "This is an arithmetic fact about timing; holds regardless of policy choices",
  "originating_agents": [
    "quant_researcher_01",
    "rates_strategist_01"
  ],
  "topic": "demographics",
  "created_at": "2026-03-23T08:13:49Z",
  "last_updated": "2026-03-23T08:13:49Z",
  "originating_iteration": "iter_0026",
  "research_iterations": 1,
  "iteration_history": [
    "iter_0026"
  ]
}
