{
  "concept_a": "roic_wacc_amplification_channel",
  "concept_b": "cross_capital_structure_compression_tail_risk",
  "mechanism": "At ROIC-WACC spreads of 3.5-5.0pp, credit spread widening mechanically increases WACC, destroying ~25% of EVA per 100bp increase, creating a feedback loop where credit deterioration causes equity fundamental impairment which causes further credit deterioration.",
  "direction": "bidirectional",
  "confidence": 7,
  "regime_dependence": "Active only when ROIC-WACC spread is tight (currently near 2007-08 levels). At wider ROIC-WACC spreads the feedback loop is much weaker.",
  "originating_agents": [
    "quant_researcher_02"
  ],
  "topic": "corporate_credit",
  "created_at": "2026-03-23T09:11:53Z",
  "last_updated": "2026-03-23T09:11:53Z",
  "originating_iteration": "iter_0029",
  "research_iterations": 1,
  "iteration_history": [
    "iter_0029"
  ]
}
