{
  "concept_a": "dollar_cycle_persistence",
  "concept_b": "transitional_oscillating_correlation",
  "mechanism": "Strong dollar (DXY 100-107) prevents the three-factor conjunction from completing, explaining why positive correlation oscillates rather than entrenching. Dollar breakdown is the missing third factor",
  "direction": "a_causes_b",
  "confidence": 6,
  "regime_dependence": "Dollar strength prevents persistent positive correlation; dollar breakdown would complete the conjunction for durable positive regime",
  "originating_agents": [
    "fx_strategist_01"
  ],
  "topic": "rates_equity_correlation",
  "created_at": "2026-03-23T04:21:39Z",
  "last_updated": "2026-03-23T04:21:39Z",
  "originating_iteration": "iter_0019",
  "research_iterations": 1,
  "iteration_history": [
    "iter_0019"
  ]
}
