{
  "slug": "august_2024_confirmation_bias",
  "definition": "The research program exhibits quantifiable confirmation bias in its treatment of the August 2024 carry unwind. The episode is cited as confirming evidence for 6+ distinct models while the 6-week full recovery updates zero models downward. The honest Bayesian update from rapid full recovery should lower the posterior on sustained systemic damage.",
  "confidence": 8.5,
  "evidence": [
    "6+ models cite August 2024 as confirming evidence",
    "6-week full recovery used to update zero models downward",
    "Debate pair_3: 'Agent B wins this one cleanly'",
    "Risk_analyst_01's response treating recovery as greater future danger is itself confirmatory behavior"
  ],
  "originating_agents": [
    "challenger_02",
    "risk_analyst_01"
  ],
  "open_questions": [
    "How much should rapid recovery lower the systemic severity posterior",
    "Whether recovery was due to structural factors (swap lines) that may not persist"
  ],
  "related_concepts": [
    "self_referential_validation_loop",
    "negative_evidence_dominance",
    "compressed_spring_probability"
  ],
  "topic": "fx_rates_divergence",
  "created_at": "2026-03-22T21:50:58Z",
  "last_updated": "2026-03-22T21:50:58Z",
  "originating_iteration": "iter_0009",
  "research_iterations": 1,
  "iteration_history": [
    "iter_0009"
  ]
}
