{
  "slug": "beautiful_deleveraging_decomposition",
  "definition": "The 1946-1980 US deleveraging decomposed approximately as: ~40% inflation, ~35% growth, ~15% primary surplus, ~10% financial repression. While based on well-documented data, the four-way split requires counterfactual assumptions, and the channels interact (inflation affects growth, primary balances are endogenous to interest rates). Modern replication is constrained by demographics and productivity gaps.",
  "confidence": 5,
  "evidence": [
    "Based on documented 1946-1980 historical data",
    "Four-channel decomposition: 40/35/15/10",
    "Counterfactual assumptions create uncertainty in the split",
    "Channels interact and are not independent",
    "Modern constraints: labor force growth ~0.3% vs. ~1.5%, productivity gaps",
    "Adjusted from 8/10 to 6-7/10 by pair_0"
  ],
  "originating_agents": [
    "generalist_02"
  ],
  "open_questions": [
    "How much do channel interactions affect the decomposition?",
    "Is the modern demographic/productivity gap a binding constraint on replication?",
    "What would a 2026 decomposition scenario look like given current constraints?"
  ],
  "related_concepts": [
    "financial_repression_modal_outcome",
    "treasury_fed_accord_precedent",
    "r_g_convergence",
    "ai_productivity_structural_break"
  ],
  "topic": "fiscal_dominance",
  "created_at": "2026-03-23T02:04:12Z",
  "last_updated": "2026-03-23T02:04:12Z",
  "originating_iteration": "iter_0016",
  "research_iterations": 1,
  "iteration_history": [
    "iter_0016"
  ]
}
