{
  "slug": "commodity_market_bifurcation",
  "definition": "Commodity markets are sending bifurcated signals that refute monolithic inflation frameworks. LME copper is in persistent backwardation ($30-80/t), crude oil in $1-2/bbl contango, aluminum in modest contango. There is no unified commodity super-cycle.",
  "confidence": 9,
  "evidence": [
    "Directly observable in futures market term structures",
    "commodities_analyst_01 assigns 9/10 (highest in their analysis)",
    "generalist_01 positive commodity-equity correlation (+0.2 to +0.3) confirms demand-pull not supply-push",
    "Oil-energy inflation pathway low probability given OPEC+ spare capacity 5-6 Mb/d",
    "Remaining risk channel is narrow: metals/power-driven inflation from copper and data center demand"
  ],
  "originating_agents": [
    "commodities_analyst_01",
    "generalist_01"
  ],
  "open_questions": [
    "Could metals/power-driven inflation alone trigger a rate shock?",
    "How does bifurcation affect traditional commodity-equity correlation models?"
  ],
  "related_concepts": [
    "copper_supply_gap",
    "opec_spare_capacity_buffer",
    "natural_gas_structural_rebasing",
    "phillips_curve_flattening"
  ],
  "topic": "equity_cycles",
  "created_at": "2026-03-24T08:24:00Z",
  "last_updated": "2026-03-24T08:24:00Z",
  "originating_iteration": "iter_0049",
  "research_iterations": 1,
  "iteration_history": [
    "iter_0049"
  ]
}
