{
  "slug": "demographic_divergence_relative_value",
  "definition": "Demographic divergence between growth economies (US via immigration, India via natural growth) and declining economies (China, Germany, Korea, Japan) creates durable but partially priced relative value opportunities across FX, equity, and rates.",
  "confidence": 6,
  "evidence": [
    "US +0.3–0.5% working-age growth vs. Japan −0.5%, China −0.3%, Korea −0.5%",
    "India +1.0% working-age growth through 2040s",
    "Maps to r* differentials and long-run FX via Balassa-Samuelson",
    "Indian equity already trades at ~22x forward P/E, embedding demographic premium"
  ],
  "originating_agents": [
    "generalist_01",
    "generalist_02",
    "credit_analyst_01",
    "rates_strategist_01"
  ],
  "open_questions": [
    "Whether US advantage survives immigration restriction",
    "Whether Indian institutional infrastructure converts demographic potential into output"
  ],
  "related_concepts": [
    "immigration_policy_demographic_variable",
    "neutral_real_rate_depression",
    "india_demographic_dividend_fragility"
  ],
  "topic": "demographics",
  "created_at": "2026-03-22T11:44:18Z",
  "last_updated": "2026-03-22T11:44:18Z",
  "originating_iteration": "iter_0001",
  "research_iterations": 1,
  "iteration_history": [
    "iter_0001"
  ]
}
