{
  "slug": "gas_oil_stranded_divergence",
  "definition": "Gas-weighted producers are fundamentally less exposed to stranded asset risk than oil-weighted producers because gas functions as a transition fuel with demand growing through 2035+ on LNG export and AI baseload demand.",
  "confidence": 7,
  "evidence": [
    "Gas demand growing through 2035+ on LNG export growth",
    "AI data center baseload power demand favoring gas",
    "Gas-weighted producers have structurally different demand trajectory from oil"
  ],
  "originating_agents": [
    "commodities_analyst_01"
  ],
  "open_questions": [
    "How long does gas transition fuel status persist before renewable baseload displaces it?",
    "Does LNG export demand growth offset domestic gas demand changes?"
  ],
  "related_concepts": [
    "stranded_fossil_asset_timeline",
    "ai_data_center_grid_competition"
  ],
  "topic": "energy_transition",
  "created_at": "2026-03-23T10:55:08Z",
  "last_updated": "2026-03-23T10:55:08Z",
  "originating_iteration": "iter_0033",
  "research_iterations": 1,
  "iteration_history": [
    "iter_0033"
  ]
}
