{
  "slug": "india_non_china_em_demand",
  "definition": "Non-China EM demand trajectory, led by India, may be larger than consensus framing suggests. India copper demand grew +9.3% YoY in FY25 to 1,878kt, projected at 3-3.3Mt by 2030. The knowledge base makes a composition fallacy by comparing India to China rather than assessing aggregate non-China EM demand — India growing from 1.9Mt to 3.3Mt is 1.4Mt incremental without replicating China.",
  "confidence": 4,
  "evidence": [
    "India copper demand +9.3% YoY in FY25 to 1,878kt",
    "Rs. 150 lakh crore National Infrastructure Pipeline (2026-32)",
    "Copper demand projected at 3-3.3Mt by 2030 (+75%)",
    "1.4Mt incremental demand does not require replicating China"
  ],
  "originating_agents": [
    "challenger_01"
  ],
  "open_questions": [
    "Can India's infrastructure pipeline deliver on schedule?",
    "What is the aggregate non-China EM demand trajectory?",
    "Does India's copper intensity follow a different development path than China's?"
  ],
  "related_concepts": [
    "copper_deficit_magnitude",
    "commodity_trifurcation"
  ],
  "topic": "commodity_supercycles",
  "created_at": "2026-03-24T09:15:33Z",
  "last_updated": "2026-03-24T09:15:33Z",
  "originating_iteration": "iter_0051",
  "research_iterations": 1,
  "iteration_history": [
    "iter_0051"
  ]
}
