{
  "slug": "new_issue_concession_widening",
  "definition": "New-issue concessions in high-yield markets have widened to 15-25bp in 2025-2026 from near-zero during QE, representing a specific and observable QT transmission channel reflecting reduced dealer balance sheet capacity and greater price sensitivity among the marginal buyer base.",
  "confidence": 7,
  "evidence": [
    "HY new-issue concessions at 15-25bp (2025-2026) vs near-zero during QE"
  ],
  "originating_agents": [
    "credit_analyst_01"
  ],
  "open_questions": [
    "Will new-issue concessions continue to widen as QT proceeds?",
    "Are current concession levels adequate to compensate for reduced dealer capacity?"
  ],
  "related_concepts": [
    "qt_term_premium_channel",
    "compound_duration_absorption"
  ],
  "topic": "central_bank_balance_sheets",
  "created_at": "2026-03-23T00:09:57Z",
  "last_updated": "2026-03-23T00:09:57Z",
  "originating_iteration": "iter_0013",
  "research_iterations": 1,
  "iteration_history": [
    "iter_0013"
  ]
}
