{
  "slug": "qe_qt_independent_channel",
  "definition": "QE/QT operates as an independent correlation channel distinct from the policy rate. QE removes duration from the private sector (correlation-suppressive); QT restores it (correlation-promoting). QT cessation (late 2026-2027) is a time-bound catalyst for correlation stabilization.",
  "confidence": 6,
  "evidence": [
    "~$1.8-2.0T shed from peak Fed balance sheet",
    "Fed cannot simultaneously tighten via QT and ease via rate cuts without contradictory signals",
    "BOJ YCC case as extreme supporting evidence",
    "Quantification of QT's specific contribution is model-dependent"
  ],
  "originating_agents": [
    "rates_strategist_02",
    "challenger_01"
  ],
  "open_questions": [
    "How much QT specifically contributes to positive correlation vs fiscal supply and inflation uncertainty",
    "Whether QT cessation alone is sufficient or merely necessary for stabilization"
  ],
  "related_concepts": [
    "maturity_dependent_correlation_bifurcation",
    "fiscal_trajectory_correlation_driver",
    "taylor_rule_inflation_coefficient"
  ],
  "topic": "rates_equity_correlation",
  "created_at": "2026-03-23T04:21:39Z",
  "last_updated": "2026-03-23T04:21:39Z",
  "originating_iteration": "iter_0019",
  "research_iterations": 1,
  "iteration_history": [
    "iter_0019"
  ]
}
