{
  "slug": "reserve_currency_exceptionalism",
  "definition": "Reserve currency status is systematically underweighted in panel-regression fiscal sustainability models. The U.S. is the only issuer of the global reserve asset (88% of FX transactions, 58% of global reserves), making treatment as one of 20 advanced economies methodologically suspect. Reserve currency status buys time (decades not years) but 'delay vs. prevent' remains unresolved.",
  "confidence": 6,
  "evidence": [
    "USD: 88% of FX transactions, 58% of global reserves",
    "Japan at 250%+ debt/GDP for 28+ years without crisis despite minor reserve status (~5% of reserves)",
    "UK Truss analogy misleading: sterling is ~5% of reserves",
    "Japan structural differences: current account surplus vs. U.S. deficit, ~90% domestic ownership vs. ~60%, deflationary vs. inflationary regime",
    "Foreign official holdings declining from 33% to 23%, replaced by structurally captive domestic institutions"
  ],
  "originating_agents": [
    "challenger_01",
    "macro_strategist_02"
  ],
  "open_questions": [
    "Does reserve currency status delay fiscal crises or prevent them entirely?",
    "How does sanctions-driven reserve diversification affect the exceptionalism argument?",
    "What is the marginal buyer composition shift doing to the demand structure for Treasuries?"
  ],
  "related_concepts": [
    "doom_loop_slow_burn",
    "sovereign_downgrade_threshold"
  ],
  "topic": "fiscal_policy",
  "created_at": "2026-03-23T11:23:51Z",
  "last_updated": "2026-03-23T11:23:51Z",
  "originating_iteration": "iter_0034",
  "research_iterations": 1,
  "iteration_history": [
    "iter_0034"
  ]
}
