{
  "slug": "telecom_capital_cycle_analogue",
  "definition": "The 1990s telecom infrastructure boom is potentially the most relevant capital cycle analogue for the energy transition: 95% company failure rate, surviving infrastructure enabled a later revolution, and median investor IRR was slightly negative. The IRA subsidy floor is a genuine structural difference that may improve investor outcomes.",
  "confidence": 6,
  "evidence": [
    "95% of telecom-era companies failed",
    "Surviving infrastructure enabled later internet revolution",
    "Median investor IRR slightly negative",
    "Value accrued to different entities than those who funded construction"
  ],
  "originating_agents": [
    "generalist_02"
  ],
  "open_questions": [
    "How much does the IRA subsidy shift the IRR distribution vs 1990s telecom?",
    "Which current clean energy companies are analogous to telecom survivors?",
    "Does regulated utility status provide better investor protection than telecom had?"
  ],
  "related_concepts": [
    "grid_modernization_investability",
    "energy_transition_timeline_overoptimism"
  ],
  "topic": "energy_transition",
  "created_at": "2026-03-23T10:55:08Z",
  "last_updated": "2026-03-23T10:55:08Z",
  "originating_iteration": "iter_0033",
  "research_iterations": 1,
  "iteration_history": [
    "iter_0033"
  ]
}
